jpeglib/__init__.py
jpeglib/_bind.py
jpeglib/_cenum.py
jpeglib/_huffman.py
jpeglib/_infere.py
jpeglib/_jpeg.py
jpeglib/_marker.py
jpeglib/_notations.py
jpeglib/_scan.py
jpeglib/dct_jpeg.py
jpeglib/functional.py
jpeglib/progressive_jpeg.py
jpeglib/spatial_jpeg.py
jpeglib/version.py
jpeglib/cjpeglib/cjpeglib_6b.abi3.so
jpeglib/cjpeglib/cjpeglib_7.abi3.so
jpeglib/cjpeglib/cjpeglib_8.abi3.so
jpeglib/cjpeglib/cjpeglib_8a.abi3.so
jpeglib/cjpeglib/cjpeglib_8b.abi3.so
jpeglib/cjpeglib/cjpeglib_8c.abi3.so
jpeglib/cjpeglib/cjpeglib_8d.abi3.so
jpeglib/cjpeglib/cjpeglib_9.abi3.so
jpeglib/cjpeglib/cjpeglib_9a.abi3.so
jpeglib/cjpeglib/cjpeglib_9b.abi3.so
jpeglib/cjpeglib/cjpeglib_9c.abi3.so
jpeglib/cjpeglib/cjpeglib_9d.abi3.so
jpeglib/cjpeglib/cjpeglib_9e.abi3.so
jpeglib/cjpeglib/cjpeglib_9f.abi3.so
jpeglib/cjpeglib/cjpeglib_common.cpp
jpeglib/cjpeglib/cjpeglib_common_flags.c
jpeglib/cjpeglib/cjpeglib_common_markers.cpp
jpeglib/cjpeglib/cjpeglib_dct.cpp
jpeglib/cjpeglib/cjpeglib_mozjpeg101.abi3.so
jpeglib/cjpeglib/cjpeglib_mozjpeg201.abi3.so
jpeglib/cjpeglib/cjpeglib_mozjpeg300.abi3.so
jpeglib/cjpeglib/cjpeglib_mozjpeg403.abi3.so
jpeglib/cjpeglib/cjpeglib_progressive.cpp
jpeglib/cjpeglib/cjpeglib_spatial.cpp
jpeglib/cjpeglib/cjpeglib_turbo120.abi3.so
jpeglib/cjpeglib/cjpeglib_turbo130.abi3.so
jpeglib/cjpeglib/cjpeglib_turbo140.abi3.so
jpeglib/cjpeglib/cjpeglib_turbo150.abi3.so
jpeglib/cjpeglib/cjpeglib_turbo200.abi3.so
jpeglib/cjpeglib/cjpeglib_turbo210.abi3.so
jpeglib/cjpeglib/6b/jcapimin.c
jpeglib/cjpeglib/6b/jcapistd.c
jpeglib/cjpeglib/6b/jccoefct.c
jpeglib/cjpeglib/6b/jccolor.c
jpeglib/cjpeglib/6b/jcdctmgr.c
jpeglib/cjpeglib/6b/jchuff.c
jpeglib/cjpeglib/6b/jcinit.c
jpeglib/cjpeglib/6b/jcmainct.c
jpeglib/cjpeglib/6b/jcmarker.c
jpeglib/cjpeglib/6b/jcmaster.c
jpeglib/cjpeglib/6b/jcomapi.c
jpeglib/cjpeglib/6b/jcparam.c
jpeglib/cjpeglib/6b/jcphuff.c
jpeglib/cjpeglib/6b/jcprepct.c
jpeglib/cjpeglib/6b/jcsample.c
jpeglib-1.0.2.dist-info/METADATA
jpeglib-1.0.2.dist-info/WHEEL
jpeglib-1.0.2.dist-info/top_level.txt
jpeglib-1.0.2.dist-info/RECORD
jpeglib-1.0.2.dist-info/licenses/LICENSE
